ovos_utterance_plugin_cancel/__init__.py
ovos_utterance_plugin_cancel/version.py
ovos_utterance_plugin_cancel/locale/ca-es/cancel.intent
ovos_utterance_plugin_cancel/locale/da-dk/cancel.intent
ovos_utterance_plugin_cancel/locale/de-de/cancel.intent
ovos_utterance_plugin_cancel/locale/en-us/cancel.intent
ovos_utterance_plugin_cancel/locale/es-es/cancel.intent
ovos_utterance_plugin_cancel/locale/fr-fr/cancel.intent
ovos_utterance_plugin_cancel/locale/gl-es/cancel.intent
ovos_utterance_plugin_cancel/locale/it-it/cancel.intent
ovos_utterance_plugin_cancel/locale/nl-nl/cancel.intent
ovos_utterance_plugin_cancel/locale/pt-br/cancel.intent
ovos_utterance_plugin_cancel/locale/pt-pt/cancel.intent
ovos_utterance_plugin_cancel-0.2.5.dist-info/LICENSE
ovos_utterance_plugin_cancel-0.2.5.dist-info/METADATA
ovos_utterance_plugin_cancel-0.2.5.dist-info/WHEEL
ovos_utterance_plugin_cancel-0.2.5.dist-info/entry_points.txt
ovos_utterance_plugin_cancel-0.2.5.dist-info/top_level.txt
ovos_utterance_plugin_cancel-0.2.5.dist-info/zip-safe
ovos_utterance_plugin_cancel-0.2.5.dist-info/RECORD
