Metadata-Version: 2.1
Name: ovos-utterance-plugin-cancel
Version: 0.2.5
Summary: OpenVoiceOS Utterance Cancel Plugin
Home-page: https://github.com/OpenVoiceOS/ovos-utterance-plugin-cancel
Author: OpenVoiceOS
Author-email: jarbasai@mailfence.com
License: apache-2.0
Classifier: Development Status :: 3 - Alpha
Classifier: Intended Audience :: Developers
Classifier: Topic :: Text Processing :: Linguistic
Classifier: License :: OSI Approved :: Apache Software License
Classifier: Programming Language :: Python :: 3.4
Classifier: Programming Language :: Python :: 3.5
Classifier: Programming Language :: Python :: 3.6
License-File: LICENSE
Requires-Dist: ovos-utils<1.0.0,>=0.6.0
